{"v":"5.7.13","fr":60,"ip":0,"op":45,"w":100,"h":100,"nm":"Save button","ddd":0,"assets":[],"layers":[{"ddd":0,"ind":1,"ty":4,"nm":"circulo","sr":1,"ks":{"o":{"a":0,"k":100,"ix":11},"r":{"a":0,"k":0,"ix":10},"p":{"a":0,"k":[50,48,0],"ix":2,"l":2},"a":{"a":0,"k":[-20.481,13.441,0],"ix":1,"l":2},"s":{"a":1,"k":[{"i":{"x":[0.667,0.667,0.667],"y":[1,1,1]},"o":{"x":[0.167,0.167,0.167],"y":[0,0,0]},"t":-5,"s":[0,0,100]},{"i":{"x":[0.667,0.667,0.667],"y":[1,1,1]},"o":{"x":[0.333,0.333,0.333],"y":[0,0,0]},"t":10,"s":[0,0,100]},{"i":{"x":[0.667,0.667,0.667],"y":[1,1,1]},"o":{"x":[0.333,0.333,0.333],"y":[0,0,0]},"t":16,"s":[240,240,100]},{"t":20,"s":[200,200,100]}],"ix":6,"l":2}},"ao":0,"shapes":[{"ty":"gr","it":[{"ind":0,"ty":"sh","ix":1,"ks":{"a":0,"k":{"i":[[7.269,0],[0,-7.269],[-7.269,0],[0,7.269]],"o":[[-7.269,0],[0,7.269],[7.269,0],[0,-7.269]],"v":[[0,-13.162],[-13.162,0],[0,13.162],[13.162,0]],"c":true},"ix":2},"nm":"Path 1","mn":"ADBE Vector Shape - Group","hd":false},{"ty":"st","c":{"a":0,"k":[1,0.776470601559,0,1],"ix":3},"o":{"a":0,"k":100,"ix":4},"w":{"a":1,"k":[{"i":{"x":[0.667],"y":[1]},"o":{"x":[0.333],"y":[0]},"t":10,"s":[10]},{"i":{"x":[0.667],"y":[1]},"o":{"x":[0.333],"y":[0]},"t":16,"s":[3]},{"t":20,"s":[0]}],"ix":5},"lc":1,"lj":1,"ml":4,"bm":0,"nm":"Stroke 1","mn":"ADBE Vector Graphic - Stroke","hd":false},{"ty":"tr","p":{"a":0,"k":[-20.481,13.441],"ix":2},"a":{"a":0,"k":[0,0],"ix":1},"s":{"a":0,"k":[100,100],"ix":3},"r":{"a":0,"k":0,"ix":6},"o":{"a":0,"k":100,"ix":7},"sk":{"a":0,"k":0,"ix":4},"sa":{"a":0,"k":0,"ix":5},"nm":"Transform"}],"nm":"Ellipse 1","np":3,"cix":2,"bm":0,"ix":1,"mn":"ADBE Vector Group","hd":false}],"ip":0,"op":45,"st":0,"bm":0},{"ddd":0,"ind":2,"ty":4,"nm":"heart-fill","sr":1,"ks":{"o":{"a":0,"k":100,"ix":11},"r":{"a":0,"k":0,"ix":10},"p":{"a":0,"k":[50,50,0],"ix":2,"l":2},"a":{"a":0,"k":[12,12,0],"ix":1,"l":2},"s":{"a":1,"k":[{"i":{"x":[0.667,0.667,0.667],"y":[1,1,1]},"o":{"x":[0.333,0.333,0.333],"y":[0,0,0]},"t":10,"s":[0,0,100]},{"i":{"x":[0.667,0.667,0.667],"y":[1,1,1]},"o":{"x":[0.333,0.333,0.333],"y":[0,0,0]},"t":18,"s":[220,220,100]},{"t":22,"s":[210,210,100]}],"ix":6,"l":2}},"ao":0,"shapes":[{"ty":"gr","it":[{"ind":0,"ty":"sh","ix":1,"ks":{"a":0,"k":{"i":[[0,5.36],[-1.034,1.016],[-1.449,-0.027],[-1.144,-1.281],[-1.718,-0.009],[-1.034,-1.016],[0,-1.45],[3.621,-3.2]],"o":[[0,-1.45],[1.034,-1.016],[1.717,-0.009],[1.144,-1.281],[1.449,-0.027],[1.035,1.016],[0,5.356],[-3.613,-3.226]],"v":[[-10,-3.587],[-8.383,-7.441],[-4.5,-8.986],[0,-6.986],[4.5,-8.986],[8.383,-7.441],[10,-3.587],[0,9.014]],"c":true},"ix":2},"nm":"Path 1","mn":"ADBE Vector Shape - Group","hd":false},{"ty":"fl","c":{"a":0,"k":[0.20000000298,0.20000000298,0.20000000298,1],"ix":4},"o":{"a":0,"k":100,"ix":5},"r":1,"bm":0,"nm":"Fill 1","mn":"ADBE Vector Graphic - Fill","hd":false},{"ty":"tr","p":{"a":0,"k":[12,11.986],"ix":2},"a":{"a":0,"k":[0,0],"ix":1},"s":{"a":0,"k":[100,100],"ix":3},"r":{"a":0,"k":0,"ix":6},"o":{"a":0,"k":100,"ix":7},"sk":{"a":0,"k":0,"ix":4},"sa":{"a":0,"k":0,"ix":5},"nm":"Transform"}],"nm":"Group 1","np":2,"cix":2,"bm":0,"ix":1,"mn":"ADBE Vector Group","hd":false}],"ip":0,"op":45,"st":0,"bm":0},{"ddd":0,"ind":3,"ty":4,"nm":"heart-outline","sr":1,"ks":{"o":{"a":0,"k":100,"ix":11},"r":{"a":0,"k":0,"ix":10},"p":{"a":0,"k":[50,49.993,0],"ix":2,"l":2},"a":{"a":0,"k":[12,12,0],"ix":1,"l":2},"s":{"a":1,"k":[{"i":{"x":[0.667,0.667,0.667],"y":[1,1,1]},"o":{"x":[0.333,0.333,0.333],"y":[0,0,0]},"t":5,"s":[210,210,100]},{"t":7,"s":[190,190,100]}],"ix":6,"l":2}},"ao":0,"shapes":[{"ty":"gr","it":[{"ind":0,"ty":"sh","ix":1,"ks":{"a":0,"k":{"i":[[1.138,-0.01],[0.67,-0.647],[-0.006,-0.905],[-0.326,-0.698],[-1.05,-0.997],[-0.986,-0.814],[-0.278,-0.227],[0,0],[-0.267,-0.222],[0,0],[0,0],[0,0],[0,0],[0,0],[0,0],[0,0],[0,0],[0,0],[0,0],[0,0],[0,0],[0,0],[0,0],[-0.273,0.225],[-0.991,1.005],[-0.641,1.299],[-0.01,0.779],[0.644,0.632],[0.933,-0.009],[0.764,-0.844],[0,0],[0,0]],"o":[[-0.932,-0.012],[-0.646,0.634],[0.011,0.77],[0.641,1.299],[0.991,1],[0.273,0.225],[0,0],[0.267,0.218],[0,0],[0,0],[0,0],[0,0],[0,0],[0,0],[0,0],[0,0],[0,0],[0,0],[0,0],[0,0],[0,0],[0,0],[0.281,-0.229],[0.986,-0.814],[1.05,-0.997],[0.332,-0.704],[0.004,-0.902],[-0.669,-0.65],[-1.138,-0.01],[0,0],[0,0],[-0.764,-0.844]],"v":[[-4.5,-6.989],[-7,-5.997],[-8,-3.589],[-7.488,-1.361],[-4.931,2.111],[-1.814,4.893],[-0.985,5.572],[-0.81,5.715],[0,6.381],[0.013,6.369],[0.019,6.364],[0.025,6.364],[0.034,6.357],[0.039,6.357],[0.044,6.357],[0.062,6.342],[0.103,6.309],[0.11,6.303],[0.121,6.295],[0.127,6.295],[0.136,6.287],[0.8,5.742],[0.974,5.599],[1.806,4.918],[4.924,2.132],[7.481,-1.339],[8,-3.589],[7,-5.989],[4.5,-6.989],[1.51,-5.678],[0,-3.938],[-1.51,-5.678]],"c":true},"ix":2},"nm":"Path 1","mn":"ADBE Vector Shape - Group","hd":false},{"ind":1,"ty":"sh","ix":2,"ks":{"a":0,"k":{"i":[[0,0],[0.771,0.633],[0,0],[1.359,3.01],[0.011,1.057],[-1.035,1.016],[-1.45,-0.03],[-0.992,-0.64],[-0.342,-0.392],[-0.435,0.285],[-1.181,0.002],[-1.034,-1.017],[0.003,-1.45],[0.447,-0.96],[2.715,-2.216],[0,0],[0.645,-0.576]],"o":[[-0.645,-0.572],[0,0],[-2.715,-2.22],[-0.446,-0.958],[-0.003,-1.45],[1.035,-1.017],[1.181,0.002],[0.436,0.283],[0.343,-0.39],[0.992,-0.64],[1.45,-0.03],[1.035,1.016],[-0.01,1.059],[-1.359,3.01],[0,0],[-0.772,0.629],[0,0]],"v":[[0,9.011],[-2.145,7.211],[-2.155,7.211],[-9.306,-0.531],[-10,-3.589],[-8.386,-7.446],[-4.5,-8.989],[-1.172,-8.006],[0,-6.989],[1.173,-8.006],[4.5,-8.989],[8.386,-7.446],[10,-3.589],[9.306,-0.526],[2.156,7.211],[2.146,7.219],[0.001,9.019]],"c":true},"ix":2},"nm":"Path 2","mn":"ADBE Vector Shape - Group","hd":false},{"ty":"mm","mm":1,"nm":"Merge Paths 1","mn":"ADBE Vector Filter - Merge","hd":false},{"ty":"fl","c":{"a":0,"k":[0.20000001496,0.20000001496,0.20000001496,1],"ix":4},"o":{"a":0,"k":100,"ix":5},"r":1,"bm":0,"nm":"Fill 1","mn":"ADBE Vector Graphic - Fill","hd":false},{"ty":"tr","p":{"a":0,"k":[12,11.989],"ix":2},"a":{"a":0,"k":[0,0],"ix":1},"s":{"a":0,"k":[100,100],"ix":3},"r":{"a":0,"k":0,"ix":6},"o":{"a":0,"k":100,"ix":7},"sk":{"a":0,"k":0,"ix":4},"sa":{"a":0,"k":0,"ix":5},"nm":"Transform"}],"nm":"Group 1","np":4,"cix":2,"bm":0,"ix":1,"mn":"ADBE Vector Group","hd":false}],"ip":0,"op":45,"st":0,"bm":0}],"markers":[]}